{
  "privacy": {
    "js": "/assets/privacy.0215518c.chunk.js"
  },
  "about": {
    "js": "/assets/about.dbae0075.chunk.js"
  },
  "register": {
    "js": "/assets/register.cadadd8a.chunk.js"
  },
  "not-found": {
    "js": "/assets/not-found.af71ec27.chunk.js"
  },
  "login": {
    "js": "/assets/login.845b3486.chunk.js"
  },
  "home": {
    "js": "/assets/home.ae1b1702.chunk.js"
  },
  "contact": {
    "js": "/assets/contact.5fb6983d.chunk.js"
  },
  "admin": {
    "js": "/assets/admin.586c4631.chunk.js"
  },
  "client": {
    "js": "/assets/client.ded4e5b5.js"
  },
  "vendor": {
    "js": "/assets/vendor.8de13771.js"
  }
}